DESCRIPTION.rst
MANIFEST.in
README.rst
setup.cfg
setup.py
pyReachAPI/__init__.py
pyReachAPI.egg-info/PKG-INFO
pyReachAPI.egg-info/SOURCES.txt
pyReachAPI.egg-info/dependency_links.txt
pyReachAPI.egg-info/requires.txt
pyReachAPI.egg-info/top_level.txt