Metadata-Version: 1.1
Name: pyReachAPI
Version: 0.0.1
Summary: A wrapper for the Halo: Reach API written in python.
Home-page: https://github.com/theJoeBiz/pyReachAPI
Author: Joe Duchnowski
Author-email: thejoebiz@gmail.com
License: MIT
Keywords: halo reach stats api xbox 360
Platform: UNKNOWN
Classifier: Development Status :: 3 - Alpha
Classifier: Intended Audience :: Developers
Classifier: Topic :: Utilities
Classifier: License :: OSI Approved :: MIT License
Classifier: Programming Language :: Python :: 2
Classifier: Programming Language :: Python :: 2.6
Classifier: Programming Language :: Python :: 2.7
Classifier: Programming Language :: Python :: 3
Classifier: Programming Language :: Python :: 3.2
Classifier: Programming Language :: Python :: 3.3
Classifier: Programming Language :: Python :: 3.4
